module_qc_data_tools/__init__.py
module_qc_data_tools/_version.py
module_qc_data_tools/_version.pyi
module_qc_data_tools/loaders.py
module_qc_data_tools/qcDataFrame.py
module_qc_data_tools/typing_compat.py
module_qc_data_tools/utils.py
module_qc_data_tools/cli/__init__.py
module_qc_data_tools/cli/__main__.py
module_qc_data_tools/cli/globals.py
module_qc_data_tools/cli/main.py
module_qc_data_tools/cli/validate.py
module_qc_data_tools/data/schema_measurement.json
module_qc_data_tools-1.3.1.dist-info/METADATA
module_qc_data_tools-1.3.1.dist-info/WHEEL
module_qc_data_tools-1.3.1.dist-info/entry_points.txt
module_qc_data_tools-1.3.1.dist-info/licenses/LICENSE
module_qc_data_tools-1.3.1.dist-info/RECORD
