Metadata-Version: 2.4
Name: module-qc-data-tools
Version: 1.3.1
Summary: Module qc data tools
Project-URL: Homepage, https://gitlab.cern.ch/atlas-itk/pixel/module/module-qc-data-tools
Project-URL: Bug Tracker, https://gitlab.cern.ch/atlas-itk/pixel/module/module-qc-data-tools/-/issues
Project-URL: Source, https://gitlab.cern.ch/atlas-itk/pixel/module/module-qc-data-tools
Project-URL: Documentation, https://atlas-itk-pixel-mqdt.docs.cern.ch/1.3/
Author-email: Jay Chan <jay.chan@cern.ch>
Maintainer-email: Giordon Stark <gstark@cern.ch>
License: Copyright (c) 2022 ATLAS ITk Pixel Modules
License-File: LICENSE
Classifier: Development Status :: 1 - Planning
Classifier: Intended Audience :: Developers
Classifier: Intended Audience :: Science/Research
Classifier: License :: OSI Approved :: MIT License
Classifier: Operating System :: OS Independent
Classifier: Programming Language :: Python
Classifier: Programming Language :: Python :: 3
Classifier: Programming Language :: Python :: 3 :: Only
Classifier: Programming Language :: Python :: 3.9
Classifier: Programming Language :: Python :: 3.10
Classifier: Programming Language :: Python :: 3.11
Classifier: Programming Language :: Python :: 3.12
Classifier: Programming Language :: Python :: 3.13
Classifier: Topic :: Scientific/Engineering
Requires-Python: >=3.9
Requires-Dist: click<8.2.0
Requires-Dist: itksn>=0.4.2
Requires-Dist: jsonschema
Requires-Dist: numpy
Requires-Dist: pymongo
Requires-Dist: rfc3339-validator
Requires-Dist: rich
Requires-Dist: tabulate
Requires-Dist: typer>=0.9.0
Requires-Dist: typing-extensions
